uniswap_smart_path/__init__.py
uniswap_smart_path/_constants.py
uniswap_smart_path/_datastructures.py
uniswap_smart_path/_utilities.py
uniswap_smart_path/exceptions.py
uniswap_smart_path/smart_path.py
uniswap_smart_path/smart_rate_limiter.py
uniswap_smart_path-0.3.0.dist-info/LICENSE
uniswap_smart_path-0.3.0.dist-info/METADATA
uniswap_smart_path-0.3.0.dist-info/WHEEL
uniswap_smart_path-0.3.0.dist-info/top_level.txt
uniswap_smart_path-0.3.0.dist-info/RECORD
