Metadata-Version: 2.1
Name: uniswap-smart-path
Version: 0.3.0
Summary: Find the path from v2 and v3 pools to swap with the best price
Author-email: Elnaril <elnaril_dev@caramail.com>
License: MIT License
Project-URL: Homepage, https://github.com/Elnaril/uniswap-smart-path
Project-URL: Bug Tracker, https://github.com/Elnaril/uniswap-smart-path/issues
Project-URL: Fiverr, https://www.fiverr.com/freelancers/elnaril
Project-URL: Buy Me A Coffee, https://www.buymeacoffee.com/elnaril
Project-URL: Malt, https://www.malt.com/profile/elnaril
Keywords: blockchain,ethereum,uniswap,exchange,dex,universal router,swap,path,route,pools
Classifier: Development Status :: 4 - Beta
Classifier: Intended Audience :: Developers
Classifier: License :: OSI Approved :: MIT License
Classifier: Natural Language :: English
Classifier: Programming Language :: Python :: 3
Classifier: Programming Language :: Python :: 3.8
Classifier: Programming Language :: Python :: 3.9
Classifier: Programming Language :: Python :: 3.10
Classifier: Programming Language :: Python :: 3.11
Classifier: Programming Language :: Python :: 3.12
Classifier: Programming Language :: Python :: 3.13
Classifier: Operating System :: OS Independent
Requires-Python: >=3.8
License-File: LICENSE
Requires-Dist: web3 <8.0.0,>=6.0.0
Requires-Dist: uniswap-universal-router-decoder >=v0.8.0
Requires-Dist: credit-rate-limit <1.0.0,>=0.2.0
